meu_primeiro_pacote/__init__.py
meu_primeiro_pacote/processing/__init__.py
meu_primeiro_pacote/processing/combination.py
meu_primeiro_pacote/processing/transformation.py
meu_primeiro_pacote/utils/__init__.py
meu_primeiro_pacote/utils/io.py
meu_primeiro_pacote/utils/plot.py
meu_primeiro_pacote.1-0.0.2.dist-info/METADATA
meu_primeiro_pacote.1-0.0.2.dist-info/WHEEL
meu_primeiro_pacote.1-0.0.2.dist-info/top_level.txt
meu_primeiro_pacote.1-0.0.2.dist-info/RECORD
