Metadata-Version: 2.1
Name: meu_primeiro_pacote.1
Version: 0.0.2
Summary: Pacote de testes da aula de criação de pacote de imagens com Python.
Home-page: https://github.com/devjeffers
Author: Jefferson
Author-email: devsfull.jefferson@gmail.com
Requires-Python: >=3.1
